LICENSE
MANIFEST.in
README.md
requirements.txt
setup.cfg
setup.py
spatialcsv/__init__.py
spatialcsv/cli.py
spatialcsv/spatialcsv.py
spatialcsv/streamlit_csv.py
spatialcsv.egg-info/PKG-INFO
spatialcsv.egg-info/SOURCES.txt
spatialcsv.egg-info/dependency_links.txt
spatialcsv.egg-info/entry_points.txt
spatialcsv.egg-info/not-zip-safe
spatialcsv.egg-info/requires.txt
spatialcsv.egg-info/top_level.txt
tests/test_spatialcsv.py