Metadata-Version: 2.1
Name: spatialcsv
Version: 0.0.19
Summary: Easily add location points to a map from a csv
Home-page: https://github.com/TJHomer/spatialcsv
Author: Tracy Homer
Author-email: thomer@mac.com
License: GNU General Public License v3
Keywords: spatialcsv
Classifier: Development Status :: 2 - Pre-Alpha
Classifier: Intended Audience :: Developers
Classifier: License :: OSI Approved :: GNU General Public License v3 (GPLv3)
Classifier: Natural Language :: English
Classifier: Programming Language :: Python :: 3
Classifier: Programming Language :: Python :: 3.7
Classifier: Programming Language :: Python :: 3.8
Classifier: Programming Language :: Python :: 3.9
Classifier: Programming Language :: Python :: 3.10
Requires-Python: >=3.7
License-File: LICENSE
